krylov/__init__.py
krylov/_helpers.py
krylov/arnoldi.py
krylov/bicg.py
krylov/bicgstab.py
krylov/cg.py
krylov/cgls.py
krylov/cgne.py
krylov/cgnr.py
krylov/cgr.py
krylov/cgs.py
krylov/chebyshev.py
krylov/craig.py
krylov/errors.py
krylov/gcr.py
krylov/givens.py
krylov/gmres.py
krylov/householder.py
krylov/lsmr.py
krylov/lsqr.py
krylov/minres.py
krylov/minres_qlp.py
krylov/qmr.py
krylov/stationary.py
krylov/symmlq.py
krylov/tfqmr.py
krylov-0.1.0.dist-info/LICENSE
krylov-0.1.0.dist-info/METADATA
krylov-0.1.0.dist-info/WHEEL
krylov-0.1.0.dist-info/top_level.txt
krylov-0.1.0.dist-info/RECORD
