Metadata-Version: 2.1
Name: krylov
Version: 0.1.0
Summary: Krylov subspace methods for Python
Home-page: https://github.com/nschloe/krylov
Author: Nico Schlömer
Author-email: nico.schloemer@gmail.com
License: MIT
Project-URL: Code, https://github.com/nschloe/krylov
Project-URL: Issues, https://github.com/nschloe/krylov/issues
Project-URL: Funding, https://github.com/sponsors/nschloe
Platform: UNKNOWN
Classifier: Development Status :: 4 - Beta
Classifier: Intended Audience :: Science/Research
Classifier: License :: OSI Approved :: MIT License
Classifier: Operating System :: OS Independent
Classifier: Programming Language :: Python
Classifier: Programming Language :: Python :: 3
Classifier: Programming Language :: Python :: 3.7
Classifier: Programming Language :: Python :: 3.8
Classifier: Programming Language :: Python :: 3.9
Classifier: Programming Language :: Python :: 3.10
Classifier: Topic :: Scientific/Engineering
Requires-Python: >=3.7
License-File: LICENSE
Requires-Dist: numpy (>=1.20.0)
Requires-Dist: scipy
Requires-Dist: importlib-metadata ; python_version < "3.8"
Requires-Dist: typing-extensions ; python_version < "3.8"
